modelhubxc_tool/cli/__init__.py
modelhubxc_tool/cli/commands/__init__.py
modelhubxc_tool/cli/commands/download.py
modelhubxc_tool/cli/commands/query.py
modelhubxc_tool/cli/config.py
modelhubxc_tool/enums.py
modelhubxc_tool/service/__init__.py
modelhubxc_tool/service/download.py
modelhubxc_tool/service/downloader/__init__.py
modelhubxc_tool/service/downloader/downloader.py
modelhubxc_tool/service/downloader/huggingface_downloader.py
modelhubxc_tool/service/downloader/modelscope_downloader.py
modelhubxc_tool/service/version_check.py
modelhubxc_tool/utils.py
modelhubxc_tool-0.1.3.dist-info/LICENSE
modelhubxc_tool-0.1.3.dist-info/METADATA
modelhubxc_tool-0.1.3.dist-info/WHEEL
modelhubxc_tool-0.1.3.dist-info/entry_points.txt
modelhubxc_tool-0.1.3.dist-info/RECORD
