Metadata-Version: 2.3
Name: modelhubxc-tool
Version: 0.1.3
Summary: A command-line tool for downloading models from ModelScope and Hugging Face platforms
Author: 张宇
Author-email: v-zhangyu03@4paradigm.com
Requires-Python: >=3.9
Classifier: Programming Language :: Python :: 3
Classifier: Programming Language :: Python :: 3.9
Classifier: Programming Language :: Python :: 3.10
Classifier: Programming Language :: Python :: 3.11
Classifier: Programming Language :: Python :: 3.12
Classifier: Programming Language :: Python :: 3.13
Requires-Dist: huggingface-hub (>=1.2.3,<2.0.0)
Requires-Dist: modelscope (>=1.33.0,<2.0.0)
Requires-Dist: pyyaml (>=6.0.3,<7.0.0)
Requires-Dist: requests (>=2.31.0,<3.0.0)
Requires-Dist: rich (>=13.0.0,<14.0.0)
Requires-Dist: typer (>=0.20.1,<0.21.0)
